{
    "configurations": [
        {
            "name": "Mac",
            "includePath": [
                "${default}",
                "${workspaceFolder}/ASCIIArt",
                "${workspaceFolder}/ASCIIArt/lib",
                "${workspaceFolder}/ASCIIArt/lib/freetype-2.13.0/include",
                "${workspaceFolder}/ASCIIArt/lib/stb"
            ],
            "defines": [],
            "macFrameworkPath": [
                "/Library/Developer/CommandLineTools/SDKs/MacOSX.sdk/System/Library/Frameworks"
            ],
            "compilerPath": "/usr/bin/clang",
            "cStandard": "c17",
            "cppStandard": "c++17",
            "intelliSenseMode": "macos-clang-arm64",
            "configurationProvider": "ms-vscode.makefile-tools"
        }
    ],
    "version": 4
}